mlflow_ray_serve/__init__.py
mlflow_ray_serve-0.2.0.dist-info/LICENSE
mlflow_ray_serve-0.2.0.dist-info/METADATA
mlflow_ray_serve-0.2.0.dist-info/WHEEL
mlflow_ray_serve-0.2.0.dist-info/entry_points.txt
mlflow_ray_serve-0.2.0.dist-info/top_level.txt
mlflow_ray_serve-0.2.0.dist-info/RECORD
