Metadata-Version: 2.1
Name: mlflow-ray-serve
Version: 0.2.0
Summary: Ray Serve MLflow deployment plugin
Home-page: https://github.com/ray-project/mlflow-ray-serve
License: Apache 2.0
Platform: UNKNOWN
License-File: LICENSE
Requires-Dist: ray[serve] (>=1.7.0)
Requires-Dist: mlflow (>=1.12.0)
